cdk_private_api_domain/__init__.py
cdk_private_api_domain/py.typed
cdk_private_api_domain/_jsii/__init__.py
cdk_private_api_domain/_jsii/cdk-private-api-domain@0.0.0.jsii.tgz
cdk_private_api_domain-0.0.0.dist-info/LICENSE
cdk_private_api_domain-0.0.0.dist-info/METADATA
cdk_private_api_domain-0.0.0.dist-info/WHEEL
cdk_private_api_domain-0.0.0.dist-info/top_level.txt
cdk_private_api_domain-0.0.0.dist-info/RECORD
